{
  "updated_at": "2026년 03월 07일 04:37 KST",
  "indices": {
    "kospi": {
      "value": 5584.87,
      "change_pct": 0.02
    },
    "kosdaq": {
      "value": 1154.67,
      "change_pct": 3.43
    },
    "sp500": {
      "value": 6764.06,
      "change_pct": -0.96
    },
    "nasdaq": {
      "value": 22525.53,
      "change_pct": -0.98
    },
    "dow": {
      "value": 47494.2,
      "change_pct": -0.95
    },
    "usdkrw": {
      "value": 1482.71,
      "change_pct": 0.16
    }
  },
  "kr": {
    "sectors": [
      {
        "name": "반도체",
        "change_pct": 2.13
      },
      {
        "name": "IT/플랫폼",
        "change_pct": 5.16
      },
      {
        "name": "금융",
        "change_pct": -1.11
      },
      {
        "name": "자동차",
        "change_pct": 1.09
      },
      {
        "name": "헬스케어",
        "change_pct": 1.88
      },
      {
        "name": "화학/에너지",
        "change_pct": -0.27
      },
      {
        "name": "철강/소재",
        "change_pct": 4.0
      },
      {
        "name": "통신",
        "change_pct": 0.27
      }
    ],
    "top_stocks": [
      {
        "ticker": "251270.KS",
        "name": "넷마블",
        "sector": "IT/플랫폼",
        "price": 54000.0,
        "change_pct": 11.34,
        "volume": 1126580,
        "trading_value": 60835320000,
        "vol_surge": 4.59,
        "score": 561.7458
      },
      {
        "ticker": "004020.KS",
        "name": "현대제철",
        "sector": "철강/소재",
        "price": 39750.0,
        "change_pct": 11.03,
        "volume": 3530672,
        "trading_value": 140344212000,
        "vol_surge": 2.92,
        "score": 359.5722
      },
      {
        "ticker": "012450.KS",
        "name": "한화에어로스페이스",
        "sector": "헬스케어",
        "price": 1481000.0,
        "change_pct": 7.24,
        "volume": 836707,
        "trading_value": 1239163067000,
        "vol_surge": 2.88,
        "score": 251.8115
      },
      {
        "ticker": "005290.KS",
        "name": "동진쎄미켐",
        "sector": "IT/플랫폼",
        "price": 55000.0,
        "change_pct": 6.38,
        "volume": 1135254,
        "trading_value": 62438970000,
        "vol_surge": 1.45,
        "score": 99.5559
      },
      {
        "ticker": "058470.KS",
        "name": "리노공업",
        "sector": "반도체",
        "price": 127000.0,
        "change_pct": 4.61,
        "volume": 1513171,
        "trading_value": 192172717000,
        "vol_surge": 1.59,
        "score": 82.6823
      },
      {
        "ticker": "042700.KS",
        "name": "한미반도체",
        "sector": "반도체",
        "price": 333500.0,
        "change_pct": 5.87,
        "volume": 2232244,
        "trading_value": 744453374000,
        "vol_surge": 1.01,
        "score": 70.4461
      },
      {
        "ticker": "035720.KS",
        "name": "카카오",
        "sector": "IT/플랫폼",
        "price": 53600.0,
        "change_pct": 4.69,
        "volume": 2823937,
        "trading_value": 151363023200,
        "vol_surge": 0.96,
        "score": 50.2566
      },
      {
        "ticker": "240810.KS",
        "name": "원익IPS",
        "sector": "반도체",
        "price": 137800.0,
        "change_pct": 3.77,
        "volume": 1010004,
        "trading_value": 139178551200,
        "vol_surge": 1.19,
        "score": 50.1248
      },
      {
        "ticker": "011170.KS",
        "name": "롯데케미칼",
        "sector": "화학/에너지",
        "price": 75400.0,
        "change_pct": 3.29,
        "volume": 231482,
        "trading_value": 17453742800,
        "vol_surge": 1.04,
        "score": 34.9305
      },
      {
        "ticker": "012330.KS",
        "name": "현대모비스",
        "sector": "자동차",
        "price": 444000.0,
        "change_pct": 2.78,
        "volume": 449828,
        "trading_value": 199723632000,
        "vol_surge": 0.94,
        "score": 29.4856
      }
    ]
  },
  "us": {
    "sectors": [
      {
        "name": "기술",
        "change_pct": -0.88
      },
      {
        "name": "금융",
        "change_pct": -1.69
      },
      {
        "name": "에너지",
        "change_pct": 0.38
      },
      {
        "name": "헬스케어",
        "change_pct": -0.63
      },
      {
        "name": "산업재",
        "change_pct": -1.16
      },
      {
        "name": "임의소비재",
        "change_pct": -1.41
      },
      {
        "name": "필수소비재",
        "change_pct": 0.11
      },
      {
        "name": "소재",
        "change_pct": -1.75
      },
      {
        "name": "부동산",
        "change_pct": -1.05
      },
      {
        "name": "유틸리티",
        "change_pct": -0.22
      },
      {
        "name": "통신서비스",
        "change_pct": -0.74
      }
    ],
    "top_stocks": [
      {
        "ticker": "COST",
        "name": "Costco Wholesale C",
        "sector": "필수소비재",
        "price": 1000.69,
        "change_pct": 2.01,
        "volume": 1661947,
        "trading_value": 1663093747,
        "vol_surge": 0.63,
        "score": 11.7521
      },
      {
        "ticker": "AEP",
        "name": "American Electric ",
        "sector": "유틸리티",
        "price": 132.24,
        "change_pct": 1.33,
        "volume": 2531632,
        "trading_value": 334783029,
        "vol_surge": 0.73,
        "score": 8.3048
      },
      {
        "ticker": "EOG",
        "name": "EOG Resources, Inc",
        "sector": "에너지",
        "price": 132.37,
        "change_pct": 1.07,
        "volume": 3828294,
        "trading_value": 506751258,
        "vol_surge": 0.79,
        "score": 7.3458
      },
      {
        "ticker": "DUK",
        "name": "Duke Energy Corpor",
        "sector": "유틸리티",
        "price": 132.2,
        "change_pct": 0.65,
        "volume": 2797614,
        "trading_value": 369844562,
        "vol_surge": 0.69,
        "score": 3.8234
      },
      {
        "ticker": "COP",
        "name": "ConocoPhillips",
        "sector": "에너지",
        "price": 117.75,
        "change_pct": 0.5,
        "volume": 6762729,
        "trading_value": 796311339,
        "vol_surge": 0.79,
        "score": 3.5086
      },
      {
        "ticker": "XOM",
        "name": "Exxon Mobil Corpor",
        "sector": "에너지",
        "price": 151.62,
        "change_pct": 0.58,
        "volume": 12226087,
        "trading_value": 1853719251,
        "vol_surge": 0.61,
        "score": 3.3034
      },
      {
        "ticker": "LLY",
        "name": "Eli Lilly and Comp",
        "sector": "헬스케어",
        "price": 988.27,
        "change_pct": 0.79,
        "volume": 1299107,
        "trading_value": 1283868500,
        "vol_surge": 0.4,
        "score": 2.9062
      },
      {
        "ticker": "D",
        "name": "Dominion Energy, I",
        "sector": "유틸리티",
        "price": 63.19,
        "change_pct": 0.29,
        "volume": 2024514,
        "trading_value": 127929036,
        "vol_surge": 0.31,
        "score": 0.7274
      },
      {
        "ticker": "CVX",
        "name": "Chevron Corporatio",
        "sector": "에너지",
        "price": 189.8,
        "change_pct": 0.05,
        "volume": 7619494,
        "trading_value": 1446218002,
        "vol_surge": 0.7,
        "score": 0.3193
      },
      {
        "ticker": "SO",
        "name": "Southern Company (",
        "sector": "유틸리티",
        "price": 97.6,
        "change_pct": -0.05,
        "volume": 3193326,
        "trading_value": 311668612,
        "vol_surge": 0.52,
        "score": -0.05
      }
    ]
  },
  "strategy": {
    "overview": "한미 증시 디커플링 뚜렷. 미국은 기술/금융 약세로 하락 마감했으나 한국은 IT/플랫폼(+5.16%), 반도체(+2.13%) 주도로 코스닥 강세(+3.43%). 원화 약세(1,482원) 지속 속 수출주 중심 순환매가 핵심 테마.",
    "action": "코스닥 IT/플랫폼 모멘텀 롱 전략 유효. 넷마블·동진쎄미켐 등 전일 급등주는 갭상승 시 추격 매수 자제, 눌림목 -3~5% 조정 시 분할 진입. 금융 섹터(-1.11%)는 단기 숏 헷지용으로 활용. 미국 선물 약세 시 장 초반 변동성 확대 구간에서 반도체 대형주 저점 매수 고려.",
    "risk": "미국 기술주 추가 하락 시 외국인 선물 매도 압력 경계. 원/달러 1,490원 돌파 시 외국인 이탈 가속화 가능. 손절 기준: 개별 종목 -4%, 지수 선물 -1.5%.",
    "watchlist": "넷마블: IT/플랫폼 대장주, +11% 급등 후 거래량 동반 여부 확인 필요\n리노공업: 반도체 검사장비 테마, 실적 모멘텀과 기술적 돌파 임박\n현대제철: 철강 리레이팅 수혜, 11% 급등 후 단기 차익실현 매물 소화 여부 관찰\n한화에어로스페이스: 방산 모멘텀 지속, 150만원 심리적 저항선 돌파 시 추가 상승 여력",
    "date": "2026년 03월 07일 04:36 KST"
  },
  "consensus": {
    "kospi": {
      "current": 5584.87,
      "target_avg": 7097,
      "upside_pct": 27.1,
      "firms_count": 27,
      "firms": [
        {
          "name": "한국투자",
          "target": 7758,
          "upside_pct": 38.9,
          "stocks": 15
        },
        {
          "name": "SK",
          "target": 7633,
          "upside_pct": 36.7,
          "stocks": 8
        },
        {
          "name": "KB",
          "target": 7588,
          "upside_pct": 35.9,
          "stocks": 10
        },
        {
          "name": "대신",
          "target": 7508,
          "upside_pct": 34.4,
          "stocks": 11
        },
        {
          "name": "미래에셋",
          "target": 7477,
          "upside_pct": 33.9,
          "stocks": 15
        },
        {
          "name": "유안타",
          "target": 7462,
          "upside_pct": 33.6,
          "stocks": 15
        },
        {
          "name": "DS투자",
          "target": 7289,
          "upside_pct": 30.5,
          "stocks": 8
        },
        {
          "name": "메리츠",
          "target": 7238,
          "upside_pct": 29.6,
          "stocks": 15
        },
        {
          "name": "다올투자",
          "target": 7221,
          "upside_pct": 29.3,
          "stocks": 14
        },
        {
          "name": "삼성",
          "target": 7220,
          "upside_pct": 29.3,
          "stocks": 15
        },
        {
          "name": "하나",
          "target": 7127,
          "upside_pct": 27.6,
          "stocks": 14
        },
        {
          "name": "한화투자",
          "target": 7125,
          "upside_pct": 27.6,
          "stocks": 12
        },
        {
          "name": "키움",
          "target": 7105,
          "upside_pct": 27.2,
          "stocks": 13
        },
        {
          "name": "NH투자",
          "target": 7077,
          "upside_pct": 26.7,
          "stocks": 14
        },
        {
          "name": "BNK투자",
          "target": 7076,
          "upside_pct": 26.7,
          "stocks": 13
        },
        {
          "name": "흥국",
          "target": 6997,
          "upside_pct": 25.3,
          "stocks": 9
        },
        {
          "name": "LS",
          "target": 6973,
          "upside_pct": 24.9,
          "stocks": 11
        },
        {
          "name": "교보",
          "target": 6965,
          "upside_pct": 24.7,
          "stocks": 7
        },
        {
          "name": "DB",
          "target": 6906,
          "upside_pct": 23.7,
          "stocks": 14
        },
        {
          "name": "iM",
          "target": 6903,
          "upside_pct": 23.6,
          "stocks": 11
        }
      ]
    },
    "kosdaq": {
      "current": 1154.67,
      "target_avg": 1242,
      "upside_pct": 7.6,
      "firms_count": 25,
      "firms": [
        {
          "name": "대신",
          "target": 1766,
          "upside_pct": 53.0,
          "stocks": 1
        },
        {
          "name": "하나",
          "target": 1557,
          "upside_pct": 34.9,
          "stocks": 3
        },
        {
          "name": "현대차",
          "target": 1545,
          "upside_pct": 33.8,
          "stocks": 1
        },
        {
          "name": "교보",
          "target": 1545,
          "upside_pct": 33.8,
          "stocks": 1
        },
        {
          "name": "다올투자",
          "target": 1475,
          "upside_pct": 27.8,
          "stocks": 2
        },
        {
          "name": "신한투자",
          "target": 1452,
          "upside_pct": 25.8,
          "stocks": 2
        },
        {
          "name": "KB",
          "target": 1426,
          "upside_pct": 23.5,
          "stocks": 1
        },
        {
          "name": "LS",
          "target": 1386,
          "upside_pct": 20.0,
          "stocks": 2
        },
        {
          "name": "흥국",
          "target": 1368,
          "upside_pct": 18.5,
          "stocks": 1
        },
        {
          "name": "NH투자",
          "target": 1280,
          "upside_pct": 10.8,
          "stocks": 2
        },
        {
          "name": "IBK투자",
          "target": 1254,
          "upside_pct": 8.6,
          "stocks": 1
        },
        {
          "name": "삼성",
          "target": 1187,
          "upside_pct": 2.8,
          "stocks": 4
        },
        {
          "name": "BNK투자",
          "target": 1163,
          "upside_pct": 0.7,
          "stocks": 2
        },
        {
          "name": "메리츠",
          "target": 1161,
          "upside_pct": 0.5,
          "stocks": 3
        },
        {
          "name": "키움",
          "target": 1156,
          "upside_pct": 0.1,
          "stocks": 2
        },
        {
          "name": "DB",
          "target": 1143,
          "upside_pct": -1.0,
          "stocks": 2
        },
        {
          "name": "미래에셋",
          "target": 1126,
          "upside_pct": -2.5,
          "stocks": 2
        },
        {
          "name": "SK",
          "target": 1109,
          "upside_pct": -3.9,
          "stocks": 2
        },
        {
          "name": "신영",
          "target": 1083,
          "upside_pct": -6.2,
          "stocks": 1
        },
        {
          "name": "DS투자",
          "target": 1077,
          "upside_pct": -6.7,
          "stocks": 3
        }
      ]
    }
  }
}