{
  "updated_at": "2026년 02월 27일 23:50 KST",
  "indices": {
    "kospi": {
      "value": 6244.13,
      "change_pct": -1.0
    },
    "kosdaq": {
      "value": 1192.78,
      "change_pct": 0.39
    },
    "sp500": {
      "value": 6849.81,
      "change_pct": -0.86
    },
    "nasdaq": {
      "value": 22659.07,
      "change_pct": -0.96
    },
    "dow": {
      "value": 48760.95,
      "change_pct": -1.49
    },
    "usdkrw": {
      "value": 1440.68,
      "change_pct": 0.51
    }
  },
  "kr": {
    "sectors": [
      {
        "name": "반도체",
        "change_pct": 4.42
      },
      {
        "name": "IT/플랫폼",
        "change_pct": -6.74
      },
      {
        "name": "금융",
        "change_pct": -3.28
      },
      {
        "name": "자동차",
        "change_pct": 4.51
      },
      {
        "name": "헬스케어",
        "change_pct": -3.3
      },
      {
        "name": "화학/에너지",
        "change_pct": 2.15
      },
      {
        "name": "철강/소재",
        "change_pct": 5.63
      },
      {
        "name": "통신",
        "change_pct": -3.8
      }
    ],
    "top_stocks": [
      {
        "ticker": "004020.KS",
        "name": "현대제철",
        "sector": "철강/소재",
        "price": 46500.0,
        "change_pct": 19.85,
        "volume": 11952358,
        "trading_value": 555784647000,
        "vol_surge": 14.95,
        "score": 2331.3639
      },
      {
        "ticker": "042700.KS",
        "name": "한미반도체",
        "sector": "반도체",
        "price": 323500.0,
        "change_pct": 17.42,
        "volume": 6899228,
        "trading_value": 2231900258000,
        "vol_surge": 3.6,
        "score": 773.5883
      },
      {
        "ticker": "011210.KS",
        "name": "현대위아",
        "sector": "자동차",
        "price": 101300.0,
        "change_pct": 9.87,
        "volume": 1604321,
        "trading_value": 162517717300,
        "vol_surge": 4.45,
        "score": 492.2311
      },
      {
        "ticker": "051910.KS",
        "name": "LG화학",
        "sector": "화학/에너지",
        "price": 417500.0,
        "change_pct": 7.05,
        "volume": 1288533,
        "trading_value": 537962527500,
        "vol_surge": 3.9,
        "score": 322.3205
      },
      {
        "ticker": "005380.KS",
        "name": "현대차",
        "sector": "자동차",
        "price": 674000.0,
        "change_pct": 10.67,
        "volume": 4354409,
        "trading_value": 2934871666000,
        "vol_surge": 1.8,
        "score": 239.8241
      },
      {
        "ticker": "011170.KS",
        "name": "롯데케미칼",
        "sector": "화학/에너지",
        "price": 95900.0,
        "change_pct": 6.56,
        "volume": 566098,
        "trading_value": 54288798200,
        "vol_surge": 2.84,
        "score": 200.169
      },
      {
        "ticker": "035720.KS",
        "name": "카카오",
        "sector": "IT/플랫폼",
        "price": 62300.0,
        "change_pct": 1.47,
        "volume": 7882544,
        "trading_value": 491082491200,
        "vol_surge": 3.03,
        "score": 52.0774
      },
      {
        "ticker": "005490.KS",
        "name": "POSCO홀딩스",
        "sector": "철강/소재",
        "price": 413000.0,
        "change_pct": 1.35,
        "volume": 819645,
        "trading_value": 338513385000,
        "vol_surge": 1.45,
        "score": 22.6082
      },
      {
        "ticker": "010140.KS",
        "name": "삼성중공업",
        "sector": "철강/소재",
        "price": 28950.0,
        "change_pct": 0.87,
        "volume": 7355652,
        "trading_value": 212946125400,
        "vol_surge": 1.45,
        "score": 14.3254
      },
      {
        "ticker": "207940.KS",
        "name": "삼성바이오로직스",
        "sector": "헬스케어",
        "price": 1778000.0,
        "change_pct": 0.68,
        "volume": 97725,
        "trading_value": 173755050000,
        "vol_surge": 1.75,
        "score": 13.3378
      }
    ]
  },
  "us": {
    "sectors": [
      {
        "name": "기술",
        "change_pct": -0.69
      },
      {
        "name": "금융",
        "change_pct": -1.87
      },
      {
        "name": "에너지",
        "change_pct": 0.63
      },
      {
        "name": "헬스케어",
        "change_pct": 0.18
      },
      {
        "name": "산업재",
        "change_pct": -0.38
      },
      {
        "name": "임의소비재",
        "change_pct": -0.33
      },
      {
        "name": "필수소비재",
        "change_pct": 0.91
      },
      {
        "name": "소재",
        "change_pct": -0.1
      },
      {
        "name": "부동산",
        "change_pct": 0.16
      },
      {
        "name": "유틸리티",
        "change_pct": 0.24
      },
      {
        "name": "통신서비스",
        "change_pct": -0.12
      }
    ],
    "top_stocks": [
      {
        "ticker": "WMT",
        "name": "Walmart Inc.",
        "sector": "필수소비재",
        "price": 126.98,
        "change_pct": 2.35,
        "volume": 3633152,
        "trading_value": 461337653,
        "vol_surge": 0.12,
        "score": 2.4095
      },
      {
        "ticker": "AMT",
        "name": "American Tower Cor",
        "sector": "부동산",
        "price": 188.43,
        "change_pct": 2.97,
        "volume": 175068,
        "trading_value": 32988061,
        "vol_surge": 0.05,
        "score": 2.233
      },
      {
        "ticker": "COP",
        "name": "ConocoPhillips",
        "sector": "에너지",
        "price": 112.41,
        "change_pct": 2.59,
        "volume": 587605,
        "trading_value": 66052680,
        "vol_surge": 0.07,
        "score": 2.0254
      },
      {
        "ticker": "EQIX",
        "name": "Equinix, Inc.",
        "sector": "부동산",
        "price": 956.46,
        "change_pct": 1.16,
        "volume": 116615,
        "trading_value": 111537001,
        "vol_surge": 0.19,
        "score": 1.7591
      },
      {
        "ticker": "MRK",
        "name": "Merck & Company, I",
        "sector": "헬스케어",
        "price": 121.33,
        "change_pct": 1.58,
        "volume": 862618,
        "trading_value": 104665754,
        "vol_surge": 0.07,
        "score": 1.2671
      },
      {
        "ticker": "XOM",
        "name": "Exxon Mobil Corpor",
        "sector": "에너지",
        "price": 150.67,
        "change_pct": 1.43,
        "volume": 1386999,
        "trading_value": 208979136,
        "vol_surge": 0.07,
        "score": 1.1898
      },
      {
        "ticker": "ABBV",
        "name": "AbbVie Inc.",
        "sector": "헬스케어",
        "price": 227.4,
        "change_pct": 1.38,
        "volume": 619900,
        "trading_value": 140965256,
        "vol_surge": 0.1,
        "score": 1.1246
      },
      {
        "ticker": "CCI",
        "name": "Crown Castle Inc.",
        "sector": "부동산",
        "price": 87.74,
        "change_pct": 1.54,
        "volume": 182220,
        "trading_value": 15987982,
        "vol_surge": 0.06,
        "score": 1.1094
      },
      {
        "ticker": "KO",
        "name": "Coca-Cola Company ",
        "sector": "필수소비재",
        "price": 81.26,
        "change_pct": 1.32,
        "volume": 1438857,
        "trading_value": 116921522,
        "vol_surge": 0.08,
        "score": 1.065
      },
      {
        "ticker": "COST",
        "name": "Costco Wholesale C",
        "sector": "필수소비재",
        "price": 993.78,
        "change_pct": 0.89,
        "volume": 167205,
        "trading_value": 166165816,
        "vol_surge": 0.06,
        "score": 0.7316
      }
    ]
  },
  "strategy": {
    "overview": "글로벌 증시 약세 속 한국시장은 혼조세로 마감. KOSPI는 1% 하락했으나 반도체(+4.42%)가 강세를 보이며 섹터 로테이션이 IT/플랫폼에서 제조업(철강, 자동차, 반도체)으로 급격히 이동 중. 원/달러 1,440원대 상승은 수출주에 긍정적이나 외국인 이탈 리스크 상존.",
    "action": "반도체·자동차 섹터 롱 포지션 유지하되, 전일 급등주(현대제철 +19.85%)는 갭 상승 시 일부 차익실현 권고. IT/플랫폼 숏 헷지 고려하며, 신규 진입은 반도체 섹터 눌림목(한미반도체 310,000원 지지선) 확인 후 분할 매수. 장 초반 30분 변동성 확인 후 포지션 확대.",
    "risk": "미국 기술주 약세(-0.96%) 지속 시 외국인 매도세 확대 가능성 주의. 원화 약세 가속화 시 외국인 수급 악화 우려. 전일 급등주 10% 이상 갭다운 시 즉시 손절, 손절 기준은 진입가 대비 -3% 엄수.",
    "watchlist": "한미반도체: 반도체 대장주로 상승 모멘텀 지속, 310K 지지 여부 확인\n현대차: 원화 약세 수혜 + 자동차 섹터 강세, 추가 상승 여력 관찰\nLG화학: 화학/2차전지 동반 상승 가능성, 420K 돌파 시 추격 매수\nNAVER: IT/플랫폼 급락(-6.74%) 후 기술적 반등 가능성, 저가 매수 타점 탐색",
    "date": "2026년 02월 27일 23:50 KST"
  }
}